constant/__init__.py
constant/constant_values.mat
constant/dirs10000.mat
constant/dirs256.mat
constant/dirs_constrained.mat
designer2/__init__.py
designer2/designer.py
designer2/tmi.py
designer2-2.0.12.data/data/constant/__init__.py
designer2-2.0.12.data/data/constant/constant_values.mat
designer2-2.0.12.data/data/constant/dirs10000.mat
designer2-2.0.12.data/data/constant/dirs256.mat
designer2-2.0.12.data/data/constant/dirs_constrained.mat
designer2.libs/libfftw3-17cc48a2.so.3.3.2
designer2.libs/libfftw3_threads-1d56c0c3.so.3.3.2
lib/__init__.py
lib/designer_fit_wrappers.py
lib/designer_func_wrappers.py
lib/designer_input_utils.py
lib/mpcomplex.py
lib/mpdenoise_adaptive.py
lib/mpunits.py
lib/rpg.cpython-310-x86_64-linux-gnu.so
lib/smi.py
lib/tensor.py
designer2-2.0.12.dist-info/METADATA
designer2-2.0.12.dist-info/WHEEL
designer2-2.0.12.dist-info/entry_points.txt
designer2-2.0.12.dist-info/top_level.txt
designer2-2.0.12.dist-info/RECORD
